src/__init__.py
src/uniqchars1/__init__.py
src/uniqchars1/main.py
src/uniqchars1/app/__init__.py
src/uniqchars1/app/app.py
src/uniqchars1/utils/__init__.py
src/uniqchars1/utils/exceptions.py
src/uniqchars1/utils/functions.py
tests/__init__.py
uniqchars1-1.3.dist-info/LICENSE
uniqchars1-1.3.dist-info/METADATA
uniqchars1-1.3.dist-info/WHEEL
uniqchars1-1.3.dist-info/entry_points.txt
uniqchars1-1.3.dist-info/top_level.txt
uniqchars1-1.3.dist-info/RECORD
